license_bb/AES_utils.py
license_bb/__init__.py
license_bb/module.py
license_bb-0.1.0.dist-info/METADATA
license_bb-0.1.0.dist-info/WHEEL
license_bb-0.1.0.dist-info/top_level.txt
license_bb-0.1.0.dist-info/RECORD
