Metadata-Version: 2.1
Name: license-bb
Version: 0.1.0
Summary: A description of your package
Home-page: https://github.com/yourusername/my_package
Author: Ambadas Dannak
Author-email: ambadas@mollatech.com
Classifier: Programming Language :: Python :: 3
Classifier: Operating System :: OS Independent
Requires-Python: >=3.8
Requires-Dist: requests
Requires-Dist: python-dateutil
Requires-Dist: schedule ==1.2.2
Requires-Dist: cryptography ==42.0.8
Requires-Dist: tzlocal ==5.2
